forestools/__init__.py
forestools/ndfiSMA.py
forestools/plot.py
forestools/pvts.py
forestools/smootH.py
forestools-0.1.2.dist-info/LICENSE
forestools-0.1.2.dist-info/METADATA
forestools-0.1.2.dist-info/WHEEL
forestools-0.1.2.dist-info/top_level.txt
forestools-0.1.2.dist-info/RECORD
