Metadata-Version: 2.1
Name: forestools
Version: 0.1.2
Summary: Tools for detecting deforestation and forest degradation
Home-page: https://github.com/ytarazona/forestools
Author: Yonatan Tarazona Coronel
Author-email: geoyons@gmail.com
License: UNKNOWN
Platform: UNKNOWN
Classifier: Programming Language :: Python :: 3
Classifier: Programming Language :: Python :: 3.5
Classifier: Programming Language :: Python :: 3.6
Classifier: Programming Language :: Python :: 3.7
Classifier: Programming Language :: Python :: 3.8
Classifier: License :: OSI Approved :: MIT License
Classifier: Natural Language :: English
Classifier: Operating System :: OS Independent
Requires-Python: >=3.5
Requires-Dist: numpy
Requires-Dist: pandas
Requires-Dist: matplotlib
Requires-Dist: datetime
